LICENSE
MANIFEST.in
README.md
setup.cfg
setup.py
wc_bankid_nbu/__init__.py
wc_bankid_nbu/client.py
wc_bankid_nbu/conf.py
wc_bankid_nbu/dtos.py
wc_bankid_nbu/exceptions.py
wc_bankid_nbu/fields.py
wc_bankid_nbu/query.py
wc_bankid_nbu/signer.py
wc_bankid_nbu/transforms.py
wc_bankid_nbu.egg-info/PKG-INFO
wc_bankid_nbu.egg-info/SOURCES.txt
wc_bankid_nbu.egg-info/dependency_links.txt
wc_bankid_nbu.egg-info/requires.txt
wc_bankid_nbu.egg-info/top_level.txt
wc_bankid_nbu/contrib/__init__.py
wc_bankid_nbu/contrib/django/__init__.py
wc_bankid_nbu/contrib/django/conf.py
wc_bankid_nbu/contrib/eu_sign/EUSignCP.py
wc_bankid_nbu/contrib/eu_sign/_EUSignCP.so
wc_bankid_nbu/contrib/eu_sign/__init__.py
wc_bankid_nbu/contrib/eu_sign/linux/32/cac.so
wc_bankid_nbu/contrib/eu_sign/linux/32/cagui.so
wc_bankid_nbu/contrib/eu_sign/linux/32/cspb.so
wc_bankid_nbu/contrib/eu_sign/linux/32/cspe.so
wc_bankid_nbu/contrib/eu_sign/linux/32/cspib.so
wc_bankid_nbu/contrib/eu_sign/linux/32/ekc1.so
wc_bankid_nbu/contrib/eu_sign/linux/32/euscp.so
wc_bankid_nbu/contrib/eu_sign/linux/32/km.eka1c.so
wc_bankid_nbu/contrib/eu_sign/linux/32/km.ekc1.so
wc_bankid_nbu/contrib/eu_sign/linux/32/km.fs.so
wc_bankid_nbu/contrib/eu_sign/linux/32/km.ncmg301.so
wc_bankid_nbu/contrib/eu_sign/linux/32/km.pkcs11.so
wc_bankid_nbu/contrib/eu_sign/linux/32/km.so
wc_bankid_nbu/contrib/eu_sign/linux/32/ldapc.so
wc_bankid_nbu/contrib/eu_sign/linux/32/libosi.so
wc_bankid_nbu/contrib/eu_sign/linux/32/nchcp.so
wc_bankid_nbu/contrib/eu_sign/linux/32/ncmg301.so
wc_bankid_nbu/contrib/eu_sign/linux/32/osplm.ini
wc_bankid_nbu/contrib/eu_sign/linux/32/pkcs11.eka1c.so
wc_bankid_nbu/contrib/eu_sign/linux/32/pkcs11.ekc1.so
wc_bankid_nbu/contrib/eu_sign/linux/32/pkif.so
wc_bankid_nbu/contrib/eu_sign/linux/64/cac.so
wc_bankid_nbu/contrib/eu_sign/linux/64/cagui.so
wc_bankid_nbu/contrib/eu_sign/linux/64/cspb.so
wc_bankid_nbu/contrib/eu_sign/linux/64/cspe.so
wc_bankid_nbu/contrib/eu_sign/linux/64/cspib.so
wc_bankid_nbu/contrib/eu_sign/linux/64/ekc1.so
wc_bankid_nbu/contrib/eu_sign/linux/64/euscp.so
wc_bankid_nbu/contrib/eu_sign/linux/64/km.eka1c.so
wc_bankid_nbu/contrib/eu_sign/linux/64/km.ekc1.so
